qmodels/__init__.py
qmodels/mg1-prio.py
qmodels/mg1-qdis.py
qmodels/mg1.py
qmodels/mm1-deque.py
qmodels/mm1-evt.py
qmodels/mm1.py
qmodels/rng.py
qmodels-1.0.1.dist-info/LICENSE
qmodels-1.0.1.dist-info/METADATA
qmodels-1.0.1.dist-info/WHEEL
qmodels-1.0.1.dist-info/top_level.txt
qmodels-1.0.1.dist-info/RECORD
