Metadata-Version: 2.1
Name: qmodels
Version: 1.0.1
Summary: Simulation of Queuing Models with Simulus
Home-page: http://qmodels.readthedocs.io/
Author: Jason Liu
Author-email: jasonxliu2010@gmail.com
License: MIT
Platform: UNKNOWN
Classifier: Development Status :: 3 - Alpha
Classifier: Programming Language :: Python :: 3
Classifier: License :: OSI Approved :: MIT License
Classifier: Operating System :: OS Independent
Requires-Python: >=3.5
Requires-Dist: simulus
Requires-Dist: numpy
Requires-Dist: scipy
Requires-Dist: matplotlib
